{"nodes": [{"id": "bitelogic_forecastviewmodel_swift", "label": "ForecastViewModel.swift", "file_type": "code", "source_file": "BiteLogic/ForecastViewModel.swift", "source_location": "L1"}, {"id": "forecastviewmodel_forecastviewmodel", "label": "ForecastViewModel", "file_type": "code", "source_file": "BiteLogic/ForecastViewModel.swift", "source_location": "L5"}, {"id": "observableobject", "label": "ObservableObject", "file_type": "code", "source_file": "", "source_location": ""}, {"id": "forecastviewmodel_forecastviewmodel_loadforecast", "label": ".loadForecast()", "file_type": "code", "source_file": "BiteLogic/ForecastViewModel.swift", "source_location": "L34"}, {"id": "forecastviewmodel_forecastviewmodel_buildforecastblocks", "label": ".buildForecastBlocks()", "file_type": "code", "source_file": "BiteLogic/ForecastViewModel.swift", "source_location": "L112"}, {"id": "forecastviewmodel_forecastviewmodel_averageinwindow", "label": ".averageInWindow()", "file_type": "code", "source_file": "BiteLogic/ForecastViewModel.swift", "source_location": "L229"}, {"id": "forecastviewmodel_forecastviewmodel_suminwindow", "label": ".sumInWindow()", "file_type": "code", "source_file": "BiteLogic/ForecastViewModel.swift", "source_location": "L236"}, {"id": "forecastviewmodel_forecastviewmodel_pressurechangerate", "label": ".pressureChangeRate()", "file_type": "code", "source_file": "BiteLogic/ForecastViewModel.swift", "source_location": "L241"}, {"id": "forecastviewmodel_forecastviewmodel_interpolatetide", "label": ".interpolateTide()", "file_type": "code", "source_file": "BiteLogic/ForecastViewModel.swift", "source_location": "L254"}, {"id": "forecastviewmodel_forecastviewmodel_parsehourlydates", "label": ".parseHourlyDates()", "file_type": "code", "source_file": "BiteLogic/ForecastViewModel.swift", "source_location": "L265"}, {"id": "forecastviewmodel_forecastviewmodel_groupbyday", "label": ".groupByDay()", "file_type": "code", "source_file": "BiteLogic/ForecastViewModel.swift", "source_location": "L272"}], "edges": [{"source": "bitelogic_forecastviewmodel_swift", "target": "foundation", "relation": "imports", "confidence": "EXTRACTED", "source_file": "BiteLogic/ForecastViewModel.swift", "source_location": "L1", "weight": 1.0}, {"source": "bitelogic_forecastviewmodel_swift", "target": "swiftui", "relation": "imports", "confidence": "EXTRACTED", "source_file": "BiteLogic/ForecastViewModel.swift", "source_location": "L2", "weight": 1.0}, {"source": "bitelogic_forecastviewmodel_swift", "target": "combine", "relation": "imports", "confidence": "EXTRACTED", "source_file": "BiteLogic/ForecastViewModel.swift", "source_location": "L3", "weight": 1.0}, {"source": "bitelogic_forecastviewmodel_swift", "target": "forecastviewmodel_forecastviewmodel", "relation": "contains", "confidence": "EXTRACTED", "source_file": "BiteLogic/ForecastViewModel.swift", "source_location": "L5", "weight": 1.0}, {"source": "forecastviewmodel_forecastviewmodel", "target": "observableobject", "relation": "inherits", "confidence": "EXTRACTED", "source_file": "BiteLogic/ForecastViewModel.swift", "source_location": "L5", "weight": 1.0}, {"source": "forecastviewmodel_forecastviewmodel", "target": "forecastviewmodel_forecastviewmodel_loadforecast", "relation": "method", "confidence": "EXTRACTED", "source_file": "BiteLogic/ForecastViewModel.swift", "source_location": "L34", "weight": 1.0}, {"source": "forecastviewmodel_forecastviewmodel", "target": "forecastviewmodel_forecastviewmodel_buildforecastblocks", "relation": "method", "confidence": "EXTRACTED", "source_file": "BiteLogic/ForecastViewModel.swift", "source_location": "L112", "weight": 1.0}, {"source": "forecastviewmodel_forecastviewmodel", "target": "forecastviewmodel_forecastviewmodel_averageinwindow", "relation": "method", "confidence": "EXTRACTED", "source_file": "BiteLogic/ForecastViewModel.swift", "source_location": "L229", "weight": 1.0}, {"source": "forecastviewmodel_forecastviewmodel", "target": "forecastviewmodel_forecastviewmodel_suminwindow", "relation": "method", "confidence": "EXTRACTED", "source_file": "BiteLogic/ForecastViewModel.swift", "source_location": "L236", "weight": 1.0}, {"source": "forecastviewmodel_forecastviewmodel", "target": "forecastviewmodel_forecastviewmodel_pressurechangerate", "relation": "method", "confidence": "EXTRACTED", "source_file": "BiteLogic/ForecastViewModel.swift", "source_location": "L241", "weight": 1.0}, {"source": "forecastviewmodel_forecastviewmodel", "target": "forecastviewmodel_forecastviewmodel_interpolatetide", "relation": "method", "confidence": "EXTRACTED", "source_file": "BiteLogic/ForecastViewModel.swift", "source_location": "L254", "weight": 1.0}, {"source": "forecastviewmodel_forecastviewmodel", "target": "forecastviewmodel_forecastviewmodel_parsehourlydates", "relation": "method", "confidence": "EXTRACTED", "source_file": "BiteLogic/ForecastViewModel.swift", "source_location": "L265", "weight": 1.0}, {"source": "forecastviewmodel_forecastviewmodel", "target": "forecastviewmodel_forecastviewmodel_groupbyday", "relation": "method", "confidence": "EXTRACTED", "source_file": "BiteLogic/ForecastViewModel.swift", "source_location": "L272", "weight": 1.0}, {"source": "forecastviewmodel_forecastviewmodel_loadforecast", "target": "forecastviewmodel_forecastviewmodel_parsehourlydates", "relation": "calls", "confidence": "EXTRACTED", "source_file": "BiteLogic/ForecastViewModel.swift", "source_location": "L70", "weight": 1.0}, {"source": "forecastviewmodel_forecastviewmodel_loadforecast", "target": "forecastviewmodel_forecastviewmodel_buildforecastblocks", "relation": "calls", "confidence": "EXTRACTED", "source_file": "BiteLogic/ForecastViewModel.swift", "source_location": "L78", "weight": 1.0}, {"source": "forecastviewmodel_forecastviewmodel_loadforecast", "target": "forecastviewmodel_forecastviewmodel_groupbyday", "relation": "calls", "confidence": "EXTRACTED", "source_file": "BiteLogic/ForecastViewModel.swift", "source_location": "L98", "weight": 1.0}, {"source": "forecastviewmodel_forecastviewmodel_buildforecastblocks", "target": "forecastviewmodel_forecastviewmodel_averageinwindow", "relation": "calls", "confidence": "EXTRACTED", "source_file": "BiteLogic/ForecastViewModel.swift", "source_location": "L139", "weight": 1.0}, {"source": "forecastviewmodel_forecastviewmodel_buildforecastblocks", "target": "forecastviewmodel_forecastviewmodel_pressurechangerate", "relation": "calls", "confidence": "EXTRACTED", "source_file": "BiteLogic/ForecastViewModel.swift", "source_location": "L152", "weight": 1.0}, {"source": "forecastviewmodel_forecastviewmodel_buildforecastblocks", "target": "forecastviewmodel_forecastviewmodel_suminwindow", "relation": "calls", "confidence": "EXTRACTED", "source_file": "BiteLogic/ForecastViewModel.swift", "source_location": "L154", "weight": 1.0}, {"source": "forecastviewmodel_forecastviewmodel_buildforecastblocks", "target": "forecastviewmodel_forecastviewmodel_interpolatetide", "relation": "calls", "confidence": "EXTRACTED", "source_file": "BiteLogic/ForecastViewModel.swift", "source_location": "L176", "weight": 1.0}], "raw_calls": [{"caller_nid": "forecastviewmodel_forecastviewmodel_loadforecast", "callee": "fetchTides3Day", "source_file": "BiteLogic/ForecastViewModel.swift", "source_location": "L44"}, {"caller_nid": "forecastviewmodel_forecastviewmodel_loadforecast", "callee": "fetchWeather3Day", "source_file": "BiteLogic/ForecastViewModel.swift", "source_location": "L54"}, {"caller_nid": "forecastviewmodel_forecastviewmodel_loadforecast", "callee": "fetchMarine3Day", "source_file": "BiteLogic/ForecastViewModel.swift", "source_location": "L62"}, {"caller_nid": "forecastviewmodel_forecastviewmodel_loadforecast", "callee": "map", "source_file": "BiteLogic/ForecastViewModel.swift", "source_location": "L71"}, {"caller_nid": "forecastviewmodel_forecastviewmodel_loadforecast", "callee": "Optional", "source_file": "BiteLogic/ForecastViewModel.swift", "source_location": "L73"}, {"caller_nid": "forecastviewmodel_forecastviewmodel_loadforecast", "callee": "map", "source_file": "BiteLogic/ForecastViewModel.swift", "source_location": "L75"}, {"caller_nid": "forecastviewmodel_forecastviewmodel_loadforecast", "callee": "map", "source_file": "BiteLogic/ForecastViewModel.swift", "source_location": "L76"}, {"caller_nid": "forecastviewmodel_forecastviewmodel_buildforecastblocks", "callee": "startOfDay", "source_file": "BiteLogic/ForecastViewModel.swift", "source_location": "L129"}, {"caller_nid": "forecastviewmodel_forecastviewmodel_buildforecastblocks", "callee": "Date", "source_file": "BiteLogic/ForecastViewModel.swift", "source_location": "L129"}, {"caller_nid": "forecastviewmodel_forecastviewmodel_buildforecastblocks", "callee": "date", "source_file": "BiteLogic/ForecastViewModel.swift", "source_location": "L133"}, {"caller_nid": "forecastviewmodel_forecastviewmodel_buildforecastblocks", "callee": "date", "source_file": "BiteLogic/ForecastViewModel.swift", "source_location": "L135"}, {"caller_nid": "forecastviewmodel_forecastviewmodel_buildforecastblocks", "callee": "date", "source_file": "BiteLogic/ForecastViewModel.swift", "source_location": "L136"}, {"caller_nid": "forecastviewmodel_forecastviewmodel_buildforecastblocks", "callee": "addingTimeInterval", "source_file": "BiteLogic/ForecastViewModel.swift", "source_location": "L137"}, {"caller_nid": "forecastviewmodel_forecastviewmodel_buildforecastblocks", "callee": "compactMap", "source_file": "BiteLogic/ForecastViewModel.swift", "source_location": "L146"}, {"caller_nid": "forecastviewmodel_forecastviewmodel_buildforecastblocks", "callee": "compactMap", "source_file": "BiteLogic/ForecastViewModel.swift", "source_location": "L161"}, {"caller_nid": "forecastviewmodel_forecastviewmodel_buildforecastblocks", "callee": "compactMap", "source_file": "BiteLogic/ForecastViewModel.swift", "source_location": "L162"}, {"caller_nid": "forecastviewmodel_forecastviewmodel_buildforecastblocks", "callee": "tideChangeRate", "source_file": "BiteLogic/ForecastViewModel.swift", "source_location": "L177"}, {"caller_nid": "forecastviewmodel_forecastviewmodel_buildforecastblocks", "callee": "blockTideInfo", "source_file": "BiteLogic/ForecastViewModel.swift", "source_location": "L178"}, {"caller_nid": "forecastviewmodel_forecastviewmodel_buildforecastblocks", "callee": "calculate", "source_file": "BiteLogic/ForecastViewModel.swift", "source_location": "L184"}, {"caller_nid": "forecastviewmodel_forecastviewmodel_buildforecastblocks", "callee": "component", "source_file": "BiteLogic/ForecastViewModel.swift", "source_location": "L185"}, {"caller_nid": "forecastviewmodel_forecastviewmodel_buildforecastblocks", "callee": "component", "source_file": "BiteLogic/ForecastViewModel.swift", "source_location": "L186"}, {"caller_nid": "forecastviewmodel_forecastviewmodel_buildforecastblocks", "callee": "EnvironmentalConditions", "source_file": "BiteLogic/ForecastViewModel.swift", "source_location": "L188"}, {"caller_nid": "forecastviewmodel_forecastviewmodel_buildforecastblocks", "callee": "Double", "source_file": "BiteLogic/ForecastViewModel.swift", "source_location": "L205"}, {"caller_nid": "forecastviewmodel_forecastviewmodel_buildforecastblocks", "callee": "preds", "source_file": "BiteLogic/ForecastViewModel.swift", "source_location": "L211"}, {"caller_nid": "forecastviewmodel_forecastviewmodel_buildforecastblocks", "callee": "predict", "source_file": "BiteLogic/ForecastViewModel.swift", "source_location": "L211"}, {"caller_nid": "forecastviewmodel_forecastviewmodel_buildforecastblocks", "callee": "append", "source_file": "BiteLogic/ForecastViewModel.swift", "source_location": "L216"}, {"caller_nid": "forecastviewmodel_forecastviewmodel_buildforecastblocks", "callee": "ForecastBlock", "source_file": "BiteLogic/ForecastViewModel.swift", "source_location": "L216"}, {"caller_nid": "forecastviewmodel_forecastviewmodel_averageinwindow", "callee": "filter", "source_file": "BiteLogic/ForecastViewModel.swift", "source_location": "L231"}, {"caller_nid": "forecastviewmodel_forecastviewmodel_averageinwindow", "callee": "zip", "source_file": "BiteLogic/ForecastViewModel.swift", "source_location": "L231"}, {"caller_nid": "forecastviewmodel_forecastviewmodel_averageinwindow", "callee": "reduce", "source_file": "BiteLogic/ForecastViewModel.swift", "source_location": "L233"}, {"caller_nid": "forecastviewmodel_forecastviewmodel_averageinwindow", "callee": "map", "source_file": "BiteLogic/ForecastViewModel.swift", "source_location": "L233"}, {"caller_nid": "forecastviewmodel_forecastviewmodel_suminwindow", "callee": "reduce", "source_file": "BiteLogic/ForecastViewModel.swift", "source_location": "L238"}, {"caller_nid": "forecastviewmodel_forecastviewmodel_suminwindow", "callee": "map", "source_file": "BiteLogic/ForecastViewModel.swift", "source_location": "L238"}, {"caller_nid": "forecastviewmodel_forecastviewmodel_suminwindow", "callee": "filter", "source_file": "BiteLogic/ForecastViewModel.swift", "source_location": "L238"}, {"caller_nid": "forecastviewmodel_forecastviewmodel_suminwindow", "callee": "zip", "source_file": "BiteLogic/ForecastViewModel.swift", "source_location": "L238"}, {"caller_nid": "forecastviewmodel_forecastviewmodel_pressurechangerate", "callee": "sorted", "source_file": "BiteLogic/ForecastViewModel.swift", "source_location": "L243"}, {"caller_nid": "forecastviewmodel_forecastviewmodel_pressurechangerate", "callee": "filter", "source_file": "BiteLogic/ForecastViewModel.swift", "source_location": "L243"}, {"caller_nid": "forecastviewmodel_forecastviewmodel_pressurechangerate", "callee": "zip", "source_file": "BiteLogic/ForecastViewModel.swift", "source_location": "L243"}, {"caller_nid": "forecastviewmodel_forecastviewmodel_pressurechangerate", "callee": "timeIntervalSince", "source_file": "BiteLogic/ForecastViewModel.swift", "source_location": "L249"}, {"caller_nid": "forecastviewmodel_forecastviewmodel_interpolatetide", "callee": "sorted", "source_file": "BiteLogic/ForecastViewModel.swift", "source_location": "L255"}, {"caller_nid": "forecastviewmodel_forecastviewmodel_interpolatetide", "callee": "firstIndex", "source_file": "BiteLogic/ForecastViewModel.swift", "source_location": "L256"}, {"caller_nid": "forecastviewmodel_forecastviewmodel_interpolatetide", "callee": "sorted", "source_file": "BiteLogic/ForecastViewModel.swift", "source_location": "L259"}, {"caller_nid": "forecastviewmodel_forecastviewmodel_interpolatetide", "callee": "sorted", "source_file": "BiteLogic/ForecastViewModel.swift", "source_location": "L260"}, {"caller_nid": "forecastviewmodel_forecastviewmodel_interpolatetide", "callee": "timeIntervalSince", "source_file": "BiteLogic/ForecastViewModel.swift", "source_location": "L261"}, {"caller_nid": "forecastviewmodel_forecastviewmodel_interpolatetide", "callee": "timeIntervalSince", "source_file": "BiteLogic/ForecastViewModel.swift", "source_location": "L261"}, {"caller_nid": "forecastviewmodel_forecastviewmodel_parsehourlydates", "callee": "DateFormatter", "source_file": "BiteLogic/ForecastViewModel.swift", "source_location": "L266"}, {"caller_nid": "forecastviewmodel_forecastviewmodel_parsehourlydates", "callee": "TimeZone", "source_file": "BiteLogic/ForecastViewModel.swift", "source_location": "L268"}, {"caller_nid": "forecastviewmodel_forecastviewmodel_parsehourlydates", "callee": "compactMap", "source_file": "BiteLogic/ForecastViewModel.swift", "source_location": "L269"}, {"caller_nid": "forecastviewmodel_forecastviewmodel_parsehourlydates", "callee": "date", "source_file": "BiteLogic/ForecastViewModel.swift", "source_location": "L269"}, {"caller_nid": "forecastviewmodel_forecastviewmodel_groupbyday", "callee": "Dictionary", "source_file": "BiteLogic/ForecastViewModel.swift", "source_location": "L274"}, {"caller_nid": "forecastviewmodel_forecastviewmodel_groupbyday", "callee": "startOfDay", "source_file": "BiteLogic/ForecastViewModel.swift", "source_location": "L275"}, {"caller_nid": "forecastviewmodel_forecastviewmodel_groupbyday", "callee": "map", "source_file": "BiteLogic/ForecastViewModel.swift", "source_location": "L277"}, {"caller_nid": "forecastviewmodel_forecastviewmodel_groupbyday", "callee": "sorted", "source_file": "BiteLogic/ForecastViewModel.swift", "source_location": "L277"}, {"caller_nid": "forecastviewmodel_forecastviewmodel_groupbyday", "callee": "ForecastDay", "source_file": "BiteLogic/ForecastViewModel.swift", "source_location": "L278"}, {"caller_nid": "forecastviewmodel_forecastviewmodel_groupbyday", "callee": "grouped", "source_file": "BiteLogic/ForecastViewModel.swift", "source_location": "L278"}]}